snakeeyes/__init__.py
snakeeyes/dice_logic.py
snakeeyes/elements.py
tests/__init__.py
tests/dice_logic_test.py
tests/elements_test.py
snakeeyes_spaceprius-0.7.1.dist-info/LICENSE.md
snakeeyes_spaceprius-0.7.1.dist-info/METADATA
snakeeyes_spaceprius-0.7.1.dist-info/WHEEL
snakeeyes_spaceprius-0.7.1.dist-info/top_level.txt
snakeeyes_spaceprius-0.7.1.dist-info/RECORD
