Metadata-Version: 2.1
Name: snakeeyes-spaceprius
Version: 0.7.1
Summary: A simple python dice library built with regex, currently in alpha
Home-page: https://github.com/SpacePrius/SnakeEyes
Author: Emily Stringer
Author-email: spaceprius@gmail.com
License: UNKNOWN
Platform: UNKNOWN
Classifier: Programming Language :: Python :: 3
Classifier: License :: OSI Approved :: MIT License
Classifier: Operating System :: OS Independent
Requires-Python: >=3.6
License-File: LICENSE.md
